scythe/__init__.py
scythe/base.py
scythe/experiments.py
scythe/hatchet.py
scythe/py.typed
scythe/registry.py
scythe/scatter_gather.py
scythe/settings.py
scythe/worker.py
scythe/utils/__init__.py
scythe/utils/filesys.py
scythe/utils/results.py
scythe/utils/s3.py
scythe_engine-0.0.38.dist-info/METADATA
scythe_engine-0.0.38.dist-info/WHEEL
scythe_engine-0.0.38.dist-info/licenses/LICENSE
scythe_engine-0.0.38.dist-info/RECORD
