Metadata-Version: 2.4
Name: scythe-engine
Version: 0.0.38
Summary: This is a repository for managing embarassingly parallel experiments with Hatchet.
Project-URL: Homepage, https://github.com/szvsw/scythe
Project-URL: Documentation, https://szvsw.github.io/scythe
Project-URL: Repository, https://github.com/szvsw/scythe
Project-URL: Issues, https://github.com/szvsw/scythe/issues
Author-email: Sam Wolk <mail@samwolk.info>
License-File: LICENSE
Requires-Python: <3.13,>=3.10
Requires-Dist: boto3<2.0,>=1.35
Requires-Dist: fastparquet~=2024.11.0
Requires-Dist: hatchet-sdk<2,>=1.16.2
Requires-Dist: numpy<2.3,>=2.2
Requires-Dist: pandas<2.3,>=2.2.2
Requires-Dist: pyarrow~=19.0.1
Requires-Dist: pydantic<3.0,>=2.9.2
Requires-Dist: tables<4.0,>=3.9
Requires-Dist: tqdm<5.0,>=4.66
